charmingbeauty/__init__.py
charmingbeauty/layout.py
charmingbeauty/logger.py
charmingbeauty/visual.py
charmingbeauty-0.1.4.dist-info/LICENSE
charmingbeauty-0.1.4.dist-info/METADATA
charmingbeauty-0.1.4.dist-info/WHEEL
charmingbeauty-0.1.4.dist-info/RECORD
