Metadata-Version: 2.1
Name: charmingbeauty
Version: 0.1.4
Summary: Beautiful plots for high energy physics (and else)
License: GPL-3
Author: Achim Stoessl
Author-email: achim.stoessl@gmail.com
Requires-Python: >=3.8,<4.0
Classifier: License :: Other/Proprietary License
Classifier: Programming Language :: Python :: 3
Classifier: Programming Language :: Python :: 3.8
Classifier: Programming Language :: Python :: 3.9
Classifier: Programming Language :: Python :: 3.10
Classifier: Programming Language :: Python :: 3.11
Requires-Dist: matplotlib (>=3.7.1,<4.0.0)
